{"name":"UGC NET CSE Exam | January 2017 | Paper 2","durationMinutes":75,"sections":[{"name":"Technical","questions":[{"id":"335161","text":"Match the following :\n\n$$\\begin{array}{llll} & \\textbf{List – I}  & {} & \\textbf{List – II} \\\\ \\text{a.} & \\text{Absurd} & \\text{i.} & \\text{Clearly impossible being contrary to some evident truth.} \\\\ \\text{b.} & \\text{Ambiguous} & \\text{ii.} & \\text{Capable of more than one interpretation or meaning.} \\\\ \\text{c.} & \\text{Axiom} & \\text{iii.} &  \\text{An assertion that is accepted and used without a proof.} \\\\ \\text{d.} & \\text{Conjecture} & \\text{iv.}& \\text{An opinion preferably based on some experience or wisdom.} \\end{array}$$\n\nCodes:\n\n$$\\begin{array}{ccccc}  & a & b & c & d \\\\ A. & i & ii & iii & iv \\\\ B. & i & iii & iv & ii \\\\ C. & ii & iii & iv & i \\\\ D. & ii & i & iii & iv \\end{array}$$","type":"MCQ","options":[{"id":"A","text":"A"},{"id":"B","text":"B"},{"id":"C","text":"C"},{"id":"D","text":"D"}],"correctAnswer":"a","marks":2,"penalty":0.6666},{"id":"335130","text":"<p>Consider the following statements related to compiler construction:</p>\n\n<ol style=\"list-style-type:upper-roman\" type=\"I\">\n\t<li>Lexical Analysis is specified by context-free grammars and implemented by pushdown automata.</li>\n</ol>\n\n<ol start=\"2\" style=\"list-style-type:upper-roman\" type=\"I\">\n\t<li>Syntax Analysis is specified by regular expressions and implemented by finite-state machine.</li>\n</ol>\n\n<p>Which of the above statement(s)&nbsp;is/are correct?</p>\n\n<ol start=\"1\" style=\"list-style-type:upper-alpha\">\n\t<li>Only I</li>\n\t<li>Only II</li>\n\t<li>Both I&nbsp;and II</li>\n\t<li>Neither I&nbsp;nor II</li>\n</ol>","type":"MCQ","options":[{"id":"A","text":"A"},{"id":"B","text":"B"},{"id":"C","text":"C"},{"id":"D","text":"D"}],"correctAnswer":"d","marks":2,"penalty":0.6666},{"id":"335116","text":"<p>__________ refers loosely to the process of semi-automatically analyzing large databases to find useful patterns.</p>\n\n<ol start=\"1\" style=\"list-style-type:upper-alpha\">\n\t<li>Datamining</li>\n\t<li>Data warehousing</li>\n\t<li>DBMS</li>\n\t<li>Data mirroring</li>\n</ol>","type":"MCQ","options":[{"id":"A","text":"A"},{"id":"B","text":"B"},{"id":"C","text":"C"},{"id":"D","text":"D"}],"correctAnswer":"a","marks":2,"penalty":0.6666},{"id":"335128","text":"<p>Which of the following statement(s)&nbsp;regarding a linker software is/are true ?</p>\n\n<ol style=\"list-style-type:upper-roman\" type=\"I\">\n\t<li>A function of a linker is to combine several object modules into a single load module.</li>\n</ol>\n\n<ol start=\"2\" style=\"list-style-type:upper-roman\" type=\"I\">\n\t<li>A function of a linker is to replace absolute references in an object module by symbolic references to locations in&nbsp;other modules.</li>\n</ol>\n\n<ol start=\"1\" style=\"list-style-type:upper-alpha\">\n\t<li>\n\t<p>Only I</p>\n\t</li>\n\t<li>\n\t<p>Only II</p>\n\t</li>\n\t<li>\n\t<p>Both I&nbsp;and II</p>\n\t</li>\n\t<li>\n\t<p>Neither I&nbsp;nor II</p>\n\t</li>\n</ol>","type":"MCQ","options":[{"id":"A","text":"A"},{"id":"B","text":"B"},{"id":"C","text":"C"},{"id":"D","text":"D"}],"correctAnswer":"a","marks":2,"penalty":0.6666},{"id":"335144","text":"<p>Consider a schema $R(MNPQ)$ and functional dependencies $M\\rightarrow N, P\\rightarrow Q$. Then the decomposition of&nbsp; $R$ into $R_{1} \\left (MN \\right )$ and&nbsp; $R_{2} \\left (PQ&nbsp;\\right )$ is __________.</p>\n\n<ol start=\"1\" style=\"list-style-type:upper-alpha\">\n\t<li>Dependency preserving but not lossless join</li>\n\t<li>Dependency preserving and lossless join</li>\n\t<li>Lossless join but not dependency preserving</li>\n\t<li>Neither dependency preserving nor lossless join.</li>\n</ol>","type":"MCQ","options":[{"id":"A","text":"A"},{"id":"B","text":"B"},{"id":"C","text":"C"},{"id":"D","text":"D"}],"correctAnswer":"a","marks":2,"penalty":0.6666},{"id":"335147","text":"<p>An attribute $A$ of datatype varchar $(20)$ has value 'Ram'&nbsp;and the attribute $B$ of datatype char $(20)$ has value 'Sita'&nbsp;in oracle. The attribute $A$ has ________ memory spaces and $B$ has _______ memory spaces.</p>\n\n<ol start=\"1\" style=\"list-style-type:upper-alpha\">\n\t<li>$20,20$</li>\n\t<li>$3,20$</li>\n\t<li>$3,4$</li>\n\t<li>$20,4$</li>\n</ol>","type":"MCQ","options":[{"id":"A","text":"A"},{"id":"B","text":"B"},{"id":"C","text":"C"},{"id":"D","text":"D"}],"correctAnswer":"b","marks":2,"penalty":0.6666},{"id":"335139","text":"<p>If $h$ is chosen from a universal collection of hash functions and is used to hash $n$ keys into a table of size $m$, where $n \\leq m$, the expected number of collisions involving a particular key $x$ is less than __________.</p>\n\n<ol start=\"1\" style=\"list-style-type:upper-alpha\">\n\t<li>$1$</li>\n\t<li>$1/n$</li>\n\t<li>$1/m$</li>\n\t<li>$n/m$</li>\n</ol>","type":"MCQ","options":[{"id":"A","text":"A"},{"id":"B","text":"B"},{"id":"C","text":"C"},{"id":"D","text":"D"}],"correctAnswer":"a","marks":2,"penalty":0.6666},{"id":"335137","text":"<p>Match the following Layers and Protocols for a user browsing with $\\text{SSL}:$<br>\n<br>\n$$\\begin{array}{clcl}  \\text{a.} &  \\text{Application of layer}  & \\text{i.} & \\text{TCP} \\\\  \\text{b.} &  \\text{Transport layer} & \\text{ii.} & \\text{IP} \\\\   \\text{c.} & \\text{Network layer} & \\text{iii.} & \\text{PPP} \\\\   \\text{d.} & \\text{Datalink layer} & \\text{iv.} & \\text{HTTP}  \\\\  \\end{array}$$</p>\n\n<p>$\\textbf{Code :}$</p>\n\n<ol start=\"1\" style=\"list-style-type:upper-alpha\">\n\t<li>$\\text{a-iv, b-i, c-ii, d-iii}$</li>\n\t<li>$\\text{a-iii, b-ii, c-i, d-iv}$</li>\n\t<li>$\\text{a-ii, b-iii, c-iv, d-i}$</li>\n\t<li>$\\text{a-iii, b-i, c-iv, d-ii}$</li>\n</ol>","type":"MCQ","options":[{"id":"A","text":"A"},{"id":"B","text":"B"},{"id":"C","text":"C"},{"id":"D","text":"D"}],"correctAnswer":"a","marks":2,"penalty":0.6666},{"id":"335126","text":"<p>In a paging system, it takes $30$ ns to search translation Look-a-side Buffer (TLB)&nbsp;and $90$ ns to access the main memory. If the TLB hit ratio is $70\\%$, the effective memory access time is :</p>\n\n<ol start=\"1\" style=\"list-style-type:upper-alpha\">\n\t<li>$48$ ns</li>\n\t<li>$147$ns</li>\n\t<li>$120$ns</li>\n\t<li>$84$ns</li>\n</ol>","type":"MCQ","options":[{"id":"A","text":"A"},{"id":"B","text":"B"},{"id":"C","text":"C"},{"id":"D","text":"D"}],"correctAnswer":"b","marks":2,"penalty":0.6666},{"id":"335138","text":"<p>Which of the following statements is false?</p>\n\n<ol start=\"1\" style=\"list-style-type:upper-alpha\">\n\t<li>Optimal binary search tree construction can be performed efficiently using dynamic programming.</li>\n\t<li>Breadth-first search cannot be used to find connected components of a graph.</li>\n\t<li>Given the prefix and postfix walks of a binary tree, the tree cannot be reconstructed uniquely.</li>\n\t<li>Depth-first-search can be used to find the connected components of a graph.&nbsp;&nbsp; &nbsp; &nbsp; &nbsp; &nbsp; &nbsp; &nbsp; &nbsp; &nbsp; &nbsp; &nbsp; &nbsp; &nbsp; &nbsp; &nbsp; &nbsp; &nbsp; &nbsp; &nbsp; &nbsp; &nbsp; &nbsp; &nbsp; &nbsp; &nbsp; &nbsp; &nbsp; &nbsp; &nbsp; &nbsp; &nbsp; &nbsp; &nbsp; &nbsp; &nbsp; &nbsp;&nbsp;</li>\n</ol>","type":"MCQ","options":[{"id":"A","text":"A"},{"id":"B","text":"B"},{"id":"C","text":"C"},{"id":"D","text":"D"}],"correctAnswer":"b","marks":2,"penalty":0.6666},{"id":"335120","text":"<p>Which of the following statement(s)&nbsp;is/are true with respect to software architecture?</p>\n\n<p>$S1$ : Coupling is a measure of how well the things grouped together in a module belong together logically.</p>\n\n<p>$S2$ : Cohesion is a measure of the degree of interaction between software modules.</p>\n\n<p>$S3$ : If coupling is low and cohesion is high then it is easier to change one module without affecting others.</p>\n\n<ol start=\"1\" style=\"list-style-type:upper-alpha\">\n\t<li>Only $S1$ and $S2$</li>\n\t<li>Only $S3$</li>\n\t<li>All of $S1$, $S2$ and $S3$</li>\n\t<li>Only $S1$</li>\n</ol>","type":"MCQ","options":[{"id":"A","text":"A"},{"id":"B","text":"B"},{"id":"C","text":"C"},{"id":"D","text":"D"}],"correctAnswer":"b","marks":2,"penalty":0.6666},{"id":"335159","text":"<p>How many multiples of $6$ are there between the following pairs of numbers?<br>\n<br>\n$0$ and $100$ and $-6$ and $34$</p>\n\n<ol start=\"1\" style=\"list-style-type:upper-alpha\">\n\t<li>$1$ and $6$</li>\n\t<li>$17$ and $6$</li>\n\t<li>$17$ and $7$</li>\n\t<li>$16$ and $7$</li>\n</ol>","type":"MCQ","options":[{"id":"A","text":"A"},{"id":"B","text":"B"},{"id":"C","text":"C"},{"id":"D","text":"D"}],"correctAnswer":"c","marks":2,"penalty":0.6666},{"id":"335124","text":"<p>Which of the following scheduling algorithms may cause starvation ?</p>\n\n<ol style=\"list-style-type:lower-alpha\" type=\"a\">\n\t<li>First-come-first-served</li>\n</ol>\n\n<ol start=\"2\" style=\"list-style-type:lower-alpha\" type=\"a\">\n\t<li>Round Robin</li>\n</ol>\n\n<ol start=\"100\" style=\"list-style-type:lower-roman\" type=\"i\">\n\t<li>Priority</li>\n</ol>\n\n<ol start=\"500\" style=\"list-style-type:lower-roman\" type=\"i\">\n\t<li>Shortest process next</li>\n</ol>\n\n<ol start=\"5\" style=\"list-style-type:lower-alpha\" type=\"a\">\n\t<li>Shortest remaining time first&nbsp;</li>\n</ol>\n\n<ol start=\"1\" style=\"list-style-type:upper-alpha\">\n\t<li>a, c&nbsp;and e</li>\n\t<li>c, d&nbsp;and e</li>\n\t<li>b, d&nbsp;and e</li>\n\t<li>b, c&nbsp;and d</li>\n</ol>","type":"MCQ","options":[{"id":"A","text":"A"},{"id":"B","text":"B"},{"id":"C","text":"C"},{"id":"D","text":"D"}],"correctAnswer":"b","marks":2,"penalty":0.6666},{"id":"335131","text":"<p>Consider the following assembly language instructions:</p>\n\n<pre class=\"prettyprint linenums lang-c_cpp\" data-pbcklang=\"c_cpp\" data-pbcktabsize=\"4\">\nmov al, 15\nmov ah, 15\nxor al, al\nmov cl, 3\nshr ax, cl\nadd al, 90H\nadd ah, 0</pre>\n\n<p>What is the value in $ax$ register after execution of above instructions?</p>\n\n<ol start=\"1\" style=\"list-style-type:upper-alpha\">\n\t<li>$0270H$</li>\n\t<li>$0170H$</li>\n\t<li>$01E0H$</li>\n\t<li>$0370H$</li>\n</ol>","type":"MCQ","options":[{"id":"A","text":"A"},{"id":"B","text":"B"},{"id":"C","text":"C"},{"id":"D","text":"D"}],"correctAnswer":"a","marks":2,"penalty":0.6666},{"id":"335122","text":"<p>Software Engineering is an engineering discipline that is concerned with:</p>\n\n<ol start=\"1\" style=\"list-style-type:upper-alpha\">\n\t<li>how computer systems work.</li>\n\t<li>theories and methods that underlie computers and software systems.</li>\n\t<li>all aspects of software production</li>\n\t<li>all aspects of computer-based systems development, including hardware, software and process engineering.</li>\n</ol>","type":"MCQ","options":[{"id":"A","text":"A"},{"id":"B","text":"B"},{"id":"C","text":"C"},{"id":"D","text":"D"}],"correctAnswer":"c","marks":2,"penalty":0.6666},{"id":"335133","text":"<p>In link state routing algorithm after construction of link state packets, new routes are computed using :</p>\n\n<ol start=\"1\" style=\"list-style-type:upper-alpha\">\n\t<li>DES&nbsp;algorithm</li>\n\t<li>Dijkstra's algorithm</li>\n\t<li>RSA&nbsp;algorithm</li>\n\t<li>Packets</li>\n</ol>","type":"MCQ","options":[{"id":"A","text":"A"},{"id":"B","text":"B"},{"id":"C","text":"C"},{"id":"D","text":"D"}],"correctAnswer":"b","marks":2,"penalty":0.6666},{"id":"335155","text":"<p>A binary $3$-bit down counter&nbsp;uses $J$-$K$ flip-flops, $FF_{i}$ with inputs $J_{i}$,&nbsp;$K_{i}$ and outputs $Q_{i}$, $i$ = $0, 1, 2$ respectively. The minimized expression for the input from following&nbsp;is :</p>\n\n<ol style=\"list-style-type:upper-roman\" type=\"I\">\n\t<li>$J_{0} = K_{0} = 0$</li>\n\t<li>$J_{0} = K_{0} = 1$</li>\n\t<li>$J_{1} = K_{1} = Q_{0}$</li>\n\t<li>$J_{1} = K_{1} = \\overline{Q}_{0}$</li>\n\t<li>$J_{2} = K_{2} =Q_{1}&nbsp;Q_{0}$</li>\n\t<li>$J_{2} = K_{2} =\\overline{Q}_{1} \\overline{Q}_{0}$</li>\n</ol>\n\n<ol style=\"list-style-type:upper-alpha\" type=\"A\">\n\t<li>I, III, V</li>\n\t<li>I, IV, VI</li>\n\t<li>II, III, V</li>\n\t<li>II, IV, VI</li>\n</ol>","type":"MCQ","options":[{"id":"A","text":"A"},{"id":"B","text":"B"},{"id":"C","text":"C"},{"id":"D","text":"D"}],"correctAnswer":"d","marks":2,"penalty":0.6666},{"id":"335125","text":"Match the following w.r.t Input/Output management :\n\n$$\\begin{array}{ll} &{\\text{List – I}}  & & {\\text{List – II}} \\\\ \\text{a.} & \\text{Device controller} & \\text{i.} & \\text{Extracts information from the controller register and store it in data buffer} \\\\ \\text{b.} & \\text{Device driver} & \\text{ii.} & \\text{I/O scheduling} \\\\ \\text{c.} & \\text{Interrupt handler} & \\text{iii.} & \\text{Performs data transfer} \\\\ \\text{d.} & \\text{Kernel I/O subsystem} & \\text{iv.} & \\text{Processing of I/O request} \\end{array}$$\n\n$$\\begin{array}{ccccc}  & a & b & c & d \\\\ \\text{A.} & iii & iv & i & ii \\\\ \\text{B.} & ii & i & iv & iii \\\\ \\text{C.} & iv & i & ii & iii \\\\ \\text{D.} & i & iii & iv & ii \\end{array}$$","type":"MCQ","options":[{"id":"A","text":"A"},{"id":"B","text":"B"},{"id":"C","text":"C"},{"id":"D","text":"D"}],"correctAnswer":"a","marks":2,"penalty":0.6666},{"id":"335145","text":"<p>Let $M$ and $N$ be two entities in an $E-R$&nbsp;diagram with simple single value attributes. $R_{1}$&nbsp;and $R_{2}$&nbsp;are two relationship between $M$ and $N$, where as $R_{1}$, is one-to-many and $R_{2}$, is many-to-many.</p>\n\n<p>The minimum number of tables required to represent $M, N, R_{1}$, and $R_{2}$, in the relational model are ___________.</p>\n\n<ol start=\"1\" style=\"list-style-type:upper-alpha\">\n\t<li>$4$</li>\n\t<li>$6$</li>\n\t<li>$7$</li>\n\t<li>$3$</li>\n</ol>","type":"MCQ","options":[{"id":"A","text":"A"},{"id":"B","text":"B"},{"id":"C","text":"C"},{"id":"D","text":"D"}],"correctAnswer":"A","marks":2,"penalty":0.6666},{"id":"335160","text":"<p>The functions mapping $R$ into $R$ are defined as :</p>\n\n<p>$f\\left(x \\right)=x^{3} - 4x, g\\left(x \\right)=\\frac{1}{x^{2}+1}$ and $h\\left(x \\right)=x^{4}.$</p>\n\n<p>Then find the value of the following composite functions :</p>\n\n<p>$h_{o}g\\left(x \\right)$ and $h_{o}g_{o}f\\left(x \\right)$</p>\n\n<ol start=\"1\" style=\"list-style-type:upper-alpha\">\n\t<li>$\\left ( x^{2}+1 \\right )^{4}$ and $\\left [ \\left ( x^{3}-4x \\right )^{2}+1 \\right ]^{4}$</li>\n\t<li>$\\left ( x^{2}+1 \\right )^{4}$ and $\\left [ \\left ( x^{3}-4x \\right )^{2}+1 \\right ]^{-4}$</li>\n\t<li>$\\left ( x^{2}+1 \\right )^{-4}$ and $\\left [ \\left ( x^{2}-4x \\right )^{2}+1 \\right ]^{4}$</li>\n\t<li>$\\left ( x^{2}+1 \\right )^{-4}$ and $\\left [ \\left ( x^{3}-4x \\right )^{2}+1 \\right ]^{-4}$</li>\n</ol>","type":"MCQ","options":[{"id":"A","text":"A"},{"id":"B","text":"B"},{"id":"C","text":"C"},{"id":"D","text":"D"}],"correctAnswer":"d","marks":2,"penalty":0.6666},{"id":"335162","text":"<p>Consider a sequence $F_{00}$ defined as :</p>\n\n<p>$F_{00}\\left ( 0 \\right )= 1, F_{00}\\left ( 1 \\right )= 1\\\\$</p>\n\n<p>$F_{00}\\left ( n \\right )= \\frac{10 * F_{00}\\left ( n-1 \\right )+100}{F_{00}\\left ( n-2 \\right )} \\text{ for }n\\geq 2 \\\\$</p>\n\n<p>Then what shall be the set of values of the sequence $F_{00}$ ?</p>\n\n<ol start=\"1\" style=\"list-style-type:upper-alpha\">\n\t<li>$\\left ( 1,110,1200 \\right )$</li>\n\t<li>$\\left ( 1,110, 600,1200 \\right )$</li>\n\t<li>$\\left ( 1, 2, 55, 110, 600, 1200 \\right )$</li>\n\t<li>$\\left ( 1, 55, 110, 600, 1200 \\right )$</li>\n</ol>","type":"MCQ","options":[{"id":"A","text":"A"},{"id":"B","text":"B"},{"id":"C","text":"C"},{"id":"D","text":"D"}],"correctAnswer":"a","marks":2,"penalty":0.6666},{"id":"335129","text":"<p>The contents of Register $(BL)$ and Register $(AL)$ of $8085$ microprocessor are $49H$ and $3AH$ respectively. The contents of $AL$, the status of carry flag $(CF)$ and sign flag $(SF)$ after executing $'SUB AL, BL'$ assembly language instruction, are</p>\n\n<ol start=\"1\" style=\"list-style-type:upper-alpha\">\n\t<li>$AL=0FH; \\: CF=1; \\: SF= 1$</li>\n\t<li>$AL = F0H; \\: CF&nbsp;= 0; \\: SF&nbsp;= 0$</li>\n\t<li>$AL =F1H; \\: CF&nbsp;= 1; \\: SF= 1$</li>\n\t<li>$AL =1FH; \\: CF=1; \\:SF=1$</li>\n</ol>","type":"MCQ","options":[{"id":"A","text":"A"},{"id":"B","text":"B"},{"id":"C","text":"C"},{"id":"D","text":"D"}],"correctAnswer":"c","marks":2,"penalty":0.6666},{"id":"335151","text":"<p>Which one of the following is correct for overloaded functions in $C++$?</p>\n\n<ol start=\"1\" style=\"list-style-type:upper-alpha\">\n\t<li>Compiler sets up a separate function for every definition of function.</li>\n\t<li>Compiler does not set up a separate function for every definition of function.</li>\n\t<li>Overloaded functions cannot handle different types of objects.</li>\n\t<li>Overloaded functions cannot have same number of arguments.</li>\n</ol>","type":"MCQ","options":[{"id":"A","text":"A"},{"id":"B","text":"B"},{"id":"C","text":"C"},{"id":"D","text":"D"}],"correctAnswer":"a","marks":2,"penalty":0.6666},{"id":"335141","text":"<p>The seven elements $A, B, C, D, E,F$ and $G$ are pushed onto a stack in reverse order, i.e., starting from $G$. The stack is popped five times and each element is inserted into a queue. Two elements are deleted from the queue and pushed back onto the stack. Now, one element is popped from the stack. The popped item is ___________.</p>\n\n<ol start=\"1\" style=\"list-style-type:upper-alpha\">\n\t<li>$A$</li>\n\t<li>$B$</li>\n\t<li>$F$</li>\n\t<li>$G$</li>\n</ol>","type":"MCQ","options":[{"id":"A","text":"A"},{"id":"B","text":"B"},{"id":"C","text":"C"},{"id":"D","text":"D"}],"correctAnswer":"b","marks":2,"penalty":0.6666},{"id":"335143","text":"<p>The order of a leaf node in a $B^{+}$ tree is the maximum number of children it can have. Suppose that block size is $1$ kilobytes, the child pointer takes $7$ bytes long and search field value takes $14$ bytes long. The order of the leaf node is _________.</p>\n\n<ol start=\"1\" style=\"list-style-type:upper-alpha\">\n\t<li>$16$</li>\n\t<li>$63$</li>\n\t<li>$64$</li>\n\t<li>$65$</li>\n</ol>","type":"MCQ","options":[{"id":"A","text":"A"},{"id":"B","text":"B"},{"id":"C","text":"C"},{"id":"D","text":"D"}],"correctAnswer":"x","marks":2,"penalty":0.6666},{"id":"335117","text":"<p>Match the following :<br>\n<br>\n$$\\begin{array}{clcl}  & \\textbf{List-I}  & {} & \\textbf{List-II} \\\\ \\text{a.} & \\text{Affiliate Marketing} & \\text{i.} & \\text{Vendors ask partners to place logos on}\\\\&&& \\text{partner’s site. If customers click, come to} \\\\&&& \\text{vendors and buy.} \\\\ \\text{b.} & \\text{Viral Marketing} & \\text{ii.} & \\text{Spread your brand on the net by} \\\\ &&& \\text{word-of-mouth. Receivers will send} \\\\ &&& \\text{your information to their friends.} \\\\ \\text{c.} & \\text{Group Purchasing} & \\text{iii.} &  \\text{Aggregating the demands of small buyers} \\\\ &&& \\text{to get a large volume. Then negotiate a price.} \\\\ \\text{d.} & \\text{Bartering Online} & \\text{iv.}& \\text{Exchanging surplus products and services} \\\\ &&& \\text{with the process administered completely} \\\\ &&& \\text{online by an intermediary. Company receives} \\\\&&& \\text{“points” for its contribution.} \\\\ \\end{array}$$<br>\n<br>\n$\\textbf{Codes :}$</p>\n\n<ol start=\"1\" style=\"list-style-type:upper-alpha\">\n\t<li>$\\text{a-i, b-ii, c-iii, d-iv}$</li>\n\t<li>$\\text{a-i, b-iii, c-ii, d-iv}$</li>\n\t<li>$\\text{a-iii, b-ii, c-iv, d-i}$</li>\n\t<li>$\\text{a-ii, b-iii, c-i, d-iv}$</li>\n</ol>","type":"MCQ","options":[{"id":"A","text":"A"},{"id":"B","text":"B"},{"id":"C","text":"C"},{"id":"D","text":"D"}],"correctAnswer":"a","marks":2,"penalty":0.6666},{"id":"335132","text":"<p>Which of the following strings would match the regular expression : $p+ [3-5] *&nbsp;&nbsp;[xyz]$?</p>\n\n<ol style=\"list-style-type:upper-roman\" type=\"I\">\n\t<li>$p443y$</li>\n\t<li>$p6y$</li>\n\t<li>$3xyz$</li>\n\t<li>$p35z$</li>\n\t<li>$p353535x$</li>\n\t<li>$ppp5$</li>\n</ol>\n\n<ol start=\"1\" style=\"list-style-type:upper-alpha\">\n\t<li>I, IlI and VI&nbsp;only</li>\n\t<li>IV, V&nbsp;and VI&nbsp;only</li>\n\t<li>II, IV&nbsp;and V&nbsp;only</li>\n\t<li>I, IV&nbsp;and V&nbsp;only</li>\n</ol>","type":"MCQ","options":[{"id":"A","text":"A"},{"id":"B","text":"B"},{"id":"C","text":"C"},{"id":"D","text":"D"}],"correctAnswer":"d","marks":2,"penalty":0.6666},{"id":"335113","text":"<p>Which of the following statements is/are true w.r.t. Enterprise Resource Planning (ERP)?</p>\n\n<ol start=\"1\" style=\"list-style-type:upper-roman\">\n\t<li>ERP&nbsp;automates and integrates majority of business processes</li>\n\t<li>ERP&nbsp;provides access to information in a Real Time Environment</li>\n\t<li>ERP&nbsp;is inexpensive to implement</li>\n</ol>\n\n<ol style=\"list-style-type:upper-alpha\" type=\"A\">\n\t<li>I, II and III are false.</li>\n\t<li>I and II false III true.</li>\n\t<li>I and II true III false.</li>\n\t<li>I&nbsp;true II and III are false.</li>\n</ol>","type":"MCQ","options":[{"id":"A","text":"A"},{"id":"B","text":"B"},{"id":"C","text":"C"},{"id":"D","text":"D"}],"correctAnswer":"c","marks":2,"penalty":0.6666},{"id":"335156","text":"<p>ECL&nbsp;is the fastest of all logic families. High speed in ECL&nbsp;is possible because transistors are used in difference amplifier configuration, in which they are never driven into ________.</p>\n\n<ol start=\"1\" style=\"list-style-type:upper-alpha\">\n\t<li>Race condition</li>\n\t<li>Saturation</li>\n\t<li>Delay</li>\n\t<li>High impedance</li>\n</ol>","type":"MCQ","options":[{"id":"A","text":"A"},{"id":"B","text":"B"},{"id":"C","text":"C"},{"id":"D","text":"D"}],"correctAnswer":"b","marks":2,"penalty":0.6666},{"id":"335154","text":"<p>Convert the octal number $0.4051$ into its equivalent decimal number.</p>\n\n<ol start=\"1\" style=\"list-style-type:upper-alpha\">\n\t<li>$0.5100098$</li>\n\t<li>$0.2096$</li>\n\t<li>$0.52$</li>\n\t<li>$0.4192$</li>\n</ol>","type":"MCQ","options":[{"id":"A","text":"A"},{"id":"B","text":"B"},{"id":"C","text":"C"},{"id":"D","text":"D"}],"correctAnswer":"a","marks":2,"penalty":0.6666},{"id":"335149","text":"<p>Which of the following operators cannot be overloaded in $\\textsf{C/C++}$ ?</p>\n\n<ol start=\"1\" style=\"list-style-type:upper-alpha\">\n\t<li>Bitwise right shift assignment</li>\n\t<li>Address of</li>\n\t<li>Indirection</li>\n\t<li>Structure reference</li>\n</ol>","type":"MCQ","options":[{"id":"A","text":"A"},{"id":"B","text":"B"},{"id":"C","text":"C"},{"id":"D","text":"D"}],"correctAnswer":"d","marks":2,"penalty":0.6666},{"id":"335140","text":"<p>Which of the following is a valid heap?</p><ol start=\"1\" style=\"list-style-type:lower-alpha\"><li><img alt=\"\" width=\"200\" height=\"193\" src=\"https://gateoverflow.in/?qa=blob&amp;qa_blobid=7828186602065247311\"></li><li><img alt=\"\" width=\"200\" height=\"193\" src=\"https://gateoverflow.in/?qa=blob&amp;qa_blobid=6294526736845332623\"></li><li><img alt=\"\" width=\"200\" height=\"193\" src=\"https://gateoverflow.in/?qa=blob&amp;qa_blobid=10333664900203391139\"></li><li><img alt=\"\" width=\"200\" height=\"190\" src=\"https://gateoverflow.in/?qa=blob&amp;qa_blobid=16318978558024358010\"></li></ol><p> </p><ol start=\"1\" style=\"list-style-type:upper-alpha\"><li>$a$</li><li>$b$</li><li>$c$</li><li>$d$</li></ol>","type":"MCQ","options":[{"id":"A","text":"A"},{"id":"B","text":"B"},{"id":"C","text":"C"},{"id":"D","text":"D"}],"correctAnswer":"b","marks":2,"penalty":0.6666},{"id":"335136","text":"<p>The maximum size of the data that the application layer can pass on to the $TCP$&nbsp;layer below is ________.</p>\n\n<ol start=\"1\" style=\"list-style-type:upper-alpha\">\n\t<li>$2^{16}$ bytes</li>\n\t<li>$2^{16}$ bytes + $TCP$ header length</li>\n\t<li>$2^{16}$ bytes – $TCP$ header length</li>\n\t<li>$2^{15}$ bytes</li>\n</ol>","type":"MCQ","options":[{"id":"A","text":"A"},{"id":"B","text":"B"},{"id":"C","text":"C"},{"id":"D","text":"D"}],"correctAnswer":"x","marks":2,"penalty":0.6666},{"id":"335118","text":"<p>A software design pattern used to enhance the functionality of an object at run-time is:</p>\n\n<ol start=\"1\" style=\"list-style-type:upper-alpha\">\n\t<li>Adapter</li>\n\t<li>Decorator</li>\n\t<li>Delegation</li>\n\t<li>Proxy</li>\n</ol>","type":"MCQ","options":[{"id":"A","text":"A"},{"id":"B","text":"B"},{"id":"C","text":"C"},{"id":"D","text":"D"}],"correctAnswer":"b","marks":2,"penalty":0.6666},{"id":"335153","text":"<p>The hexadecimal equivalent of the octal number $2357$ is :</p>\n\n<ol start=\"1\" style=\"list-style-type:upper-alpha\">\n\t<li>$2EE$</li>\n\t<li>$2FF$</li>\n\t<li>$4EF$</li>\n\t<li>$4FE$</li>\n</ol>","type":"MCQ","options":[{"id":"A","text":"A"},{"id":"B","text":"B"},{"id":"C","text":"C"},{"id":"D","text":"D"}],"correctAnswer":"c","marks":2,"penalty":0.6666},{"id":"335127","text":"<p>There are three processes $P_{1}, P_{2}$ and $P_{3}$&nbsp;sharing a semaphore for synchronizing a variable. Initial value of semaphore is one. Assume that negative value of semaphore tells us how many processes are waiting in queue. Processes access the semaphore in following order :</p>\n\n<ol style=\"list-style-type:lower-alpha\" type=\"a\">\n\t<li>$P2$ needs to access</li>\n</ol>\n\n<ol start=\"2\" style=\"list-style-type:lower-alpha\" type=\"a\">\n\t<li>$P1$ needs to access</li>\n</ol>\n\n<ol start=\"100\" style=\"list-style-type:lower-roman\" type=\"i\">\n\t<li>$P3$ needs to access</li>\n</ol>\n\n<ol start=\"500\" style=\"list-style-type:lower-roman\" type=\"i\">\n\t<li>$P2$ exits critical section</li>\n</ol>\n\n<ol start=\"5\" style=\"list-style-type:lower-alpha\" type=\"a\">\n\t<li>$P1$ exits critical section</li>\n</ol>\n\n<p>The final value of semaphore will be :</p>\n\n<ol start=\"1\" style=\"list-style-type:upper-alpha\">\n\t<li>$0$</li>\n\t<li>$1$</li>\n\t<li>$-1$</li>\n\t<li>$-2$</li>\n</ol>","type":"MCQ","options":[{"id":"A","text":"A"},{"id":"B","text":"B"},{"id":"C","text":"C"},{"id":"D","text":"D"}],"correctAnswer":"a","marks":2,"penalty":0.6666},{"id":"335121","text":"<p>Which of the following is not one of three software product aspects addressed by McCall's software quality factors ?</p>\n\n<ol start=\"1\" style=\"list-style-type:upper-alpha\">\n\t<li>Ability to undergo change</li>\n\t<li>Adaptiability to new environments</li>\n\t<li>Operational characteristics</li>\n\t<li>Production costs and scheduling</li>\n</ol>","type":"MCQ","options":[{"id":"A","text":"A"},{"id":"B","text":"B"},{"id":"C","text":"C"},{"id":"D","text":"D"}],"correctAnswer":"d","marks":2,"penalty":0.6666},{"id":"335115","text":"<p>Which of the following is/are true w.r.t. applications of mobile computing?</p>\n\n<ol start=\"1\" style=\"list-style-type:lower-alpha\">\n\t<li>Travelling of salesman</li>\n\t<li>Location awareness services</li>\n</ol>\n\n<ol start=\"1\" style=\"list-style-type:upper-alpha\">\n\t<li>a true; b false.</li>\n\t<li>Both a and b are true.</li>\n\t<li>Both a and b are false.</li>\n\t<li>a false; b true.</li>\n</ol>","type":"MCQ","options":[{"id":"A","text":"A"},{"id":"B","text":"B"},{"id":"C","text":"C"},{"id":"D","text":"D"}],"correctAnswer":"b","marks":2,"penalty":0.6666},{"id":"335142","text":"<p>Which of the following is true for computation time in insertion, deletion and finding maximum and minimum element in a sorted array ?</p>\n\n<ol start=\"1\" style=\"list-style-type:upper-alpha\">\n\t<li>Insertion – $0(1)$, Deletion – $0(1)$, Maximum – $0(1)$, Minimum – $0(1)$</li>\n\t<li>Insertion – $0(1)$, Deletion – $0(1)$, Maximum – $0(n)$, Minimum – $0(n)$</li>\n\t<li>Insertion – $0(n)$, Deletion – $0(n)$, Maximum – $0(1)$, Minimum – $0(1)$</li>\n\t<li>Insertion –&nbsp; $0(n)$, Deletion – $0(n)$, Maximum – $0(n)$, Minimum – $0(n)$</li>\n</ol>","type":"MCQ","options":[{"id":"A","text":"A"},{"id":"B","text":"B"},{"id":"C","text":"C"},{"id":"D","text":"D"}],"correctAnswer":"c","marks":2,"penalty":0.6666},{"id":"335157","text":"<p>In propositional logic if&nbsp;$\\left ( P \\rightarrow Q \\right )\\wedge \\left ( R \\rightarrow S \\right )$ and $\\left ( P \\vee R \\right )$&nbsp;are two premises such that</p>\n\n<p>$$\\begin{array}{c} (P \\to Q) \\wedge (R \\to S) \\\\&nbsp; P \\vee R&nbsp;\\\\ \\hline Y \\\\ \\hline \\end{array}$$</p>\n\n<p>$Y$&nbsp;is the premise :</p>\n\n<ol start=\"1\" style=\"list-style-type:upper-alpha\">\n\t<li>$P \\vee R$</li>\n\t<li>$P&nbsp;\\vee S$</li>\n\t<li>$Q \\vee R$</li>\n\t<li>$Q \\vee S$</li>\n</ol>","type":"MCQ","options":[{"id":"A","text":"A"},{"id":"B","text":"B"},{"id":"C","text":"C"},{"id":"D","text":"D"}],"correctAnswer":"A;B;C;D","marks":2,"penalty":0.6666},{"id":"335119","text":"<p>The prototyping model of software development is:</p>\n\n<ol start=\"1\" style=\"list-style-type:upper-alpha\">\n\t<li>a reasonable approach when requirements are well-defined.</li>\n\t<li>a useful approach when a customer cannot define requirements clearly.</li>\n\t<li>the best approach to use for projects with large development teams.</li>\n\t<li>a risky model that rarely produces a meaningful product.</li>\n</ol>","type":"MCQ","options":[{"id":"A","text":"A"},{"id":"B","text":"B"},{"id":"C","text":"C"},{"id":"D","text":"D"}],"correctAnswer":"b","marks":2,"penalty":0.6666},{"id":"335148","text":"<p>If $X$ is a binary number which is power of $2$, then the value of $X&nbsp;\\&amp; (X-1)$ is :</p>\n\n<ol start=\"1\" style=\"list-style-type:upper-alpha\">\n\t<li>$11\\dots11$</li>\n\t<li>$00\\dots00$</li>\n\t<li>$100\\dots0$</li>\n\t<li>$000\\dots1$</li>\n</ol>","type":"MCQ","options":[{"id":"A","text":"A"},{"id":"B","text":"B"},{"id":"C","text":"C"},{"id":"D","text":"D"}],"correctAnswer":"b","marks":2,"penalty":0.6666},{"id":"335114","text":"<p>In $3G$ network, $\\text{W-CDMA}$ is also known as $\\text{UMTS}$. The minimum spectrum allocation required for $\\text{W-CDMA}$ is</p>\n\n<ol start=\"1\" style=\"list-style-type:upper-alpha\">\n\t<li>$2$ MHz</li>\n\t<li>$20$ KHz</li>\n\t<li>$5$ KHz</li>\n\t<li>$5$ MHz</li>\n</ol>","type":"MCQ","options":[{"id":"A","text":"A"},{"id":"B","text":"B"},{"id":"C","text":"C"},{"id":"D","text":"D"}],"correctAnswer":"d","marks":2,"penalty":0.6666},{"id":"335158","text":"<p>Consider a Hamiltonian Graph $G$ with no loops or parallel edges and with&nbsp;$\\left | V\\left ( G \\right ) \\right |= n\\geq 3$. The which of the following is true?</p>\n\n<ol style=\"list-style-type:upper-alpha\" type=\"A\">\n\t<li>$\\text{deg}\\left ( v \\right )\\geq \\frac{n}{2}$ for each vertex $v\\\\$</li>\n\t<li>$\\left | E\\left ( G \\right ) \\right |\\geq \\frac{1}{2}\\left ( n-1 \\right )\\left ( n-2 \\right )+2 \\\\$</li>\n\t<li>$\\text{deg}\\left ( v \\right )+\\text{deg}\\left ( w \\right )\\geq n$ whenever $v$ and $w$ are not connected by an edge</li>\n\t<li>All of the above</li>\n</ol>","type":"MCQ","options":[{"id":"A","text":"A"},{"id":"B","text":"B"},{"id":"C","text":"C"},{"id":"D","text":"D"}],"correctAnswer":"d","marks":2,"penalty":0.6666},{"id":"335135","text":"<p>A packet whose destination is outside the local $TCP/IP$ network segment is sent to ________.</p>\n\n<ol start=\"1\" style=\"list-style-type:upper-alpha\">\n\t<li>File server</li>\n\t<li>$DNS$ server</li>\n\t<li>$DHCP$ server</li>\n\t<li>Default gateway</li>\n</ol>","type":"MCQ","options":[{"id":"A","text":"A"},{"id":"B","text":"B"},{"id":"C","text":"C"},{"id":"D","text":"D"}],"correctAnswer":"d","marks":2,"penalty":0.6666},{"id":"335150","text":"<p>Which of the following storage classes have global visibility in $C/C++$?</p>\n\n<ol start=\"1\" style=\"list-style-type:upper-alpha\">\n\t<li>Auto</li>\n\t<li>Extern</li>\n\t<li>Static</li>\n\t<li>Register</li>\n</ol>","type":"MCQ","options":[{"id":"A","text":"A"},{"id":"B","text":"B"},{"id":"C","text":"C"},{"id":"D","text":"D"}],"correctAnswer":"b","marks":2,"penalty":0.6666},{"id":"335146","text":"<p>Integrity constraints ensure that changes made to the database by authorized users do not result into loss of data consistency. Which of the following statement(s) is (are) true w.r.t.the examples of integrity constraints?</p>\n\n<ol start=\"1\" style=\"list-style-type:lower-roman\">\n\t<li>An instructor Id. No. cannot be null, provided Instructor&nbsp; Id No. being primary key.</li>\n\t<li>No two citizens have same Adhar-ld.</li>\n\t<li>Budget of a company must be zero.</li>\n</ol>\n\n<ol start=\"1\" style=\"list-style-type:upper-alpha\">\n\t<li>a, b and c are true.</li>\n\t<li>a false, b and c are true.</li>\n\t<li>a and b are true;&nbsp;c false.</li>\n\t<li>a,b and c are false.</li>\n</ol>","type":"MCQ","options":[{"id":"A","text":"A"},{"id":"B","text":"B"},{"id":"C","text":"C"},{"id":"D","text":"D"}],"correctAnswer":"c","marks":2,"penalty":0.6666},{"id":"335123","text":"<p>Distributed operating systems consist of:</p>\n\n<ol start=\"1\" style=\"list-style-type:upper-alpha\">\n\t<li>Loosely coupled O.S.&nbsp;software on a loosely coupled hardware.</li>\n\t<li>Loosely coupled O.S.&nbsp;software on a tightly coupled hardware.</li>\n\t<li>Tightly coupled O.S.&nbsp;software on a loosely coupled hardware.</li>\n\t<li>Tightly coupled O.S.&nbsp;software on a tightly coupled hardware.</li>\n</ol>","type":"MCQ","options":[{"id":"A","text":"A"},{"id":"B","text":"B"},{"id":"C","text":"C"},{"id":"D","text":"D"}],"correctAnswer":"c","marks":2,"penalty":0.6666},{"id":"335134","text":"<p>Distance vector routing algorithm is a dynamic routing algorithm. The routing tables in distance vector routing algorithm are updated __________.</p>\n\n<ol start=\"1\" style=\"list-style-type:upper-alpha\">\n\t<li>automatically</li>\n\t<li>by server</li>\n\t<li>by exchanging information with neighbour nodes</li>\n\t<li>with back up database</li>\n</ol>","type":"MCQ","options":[{"id":"A","text":"A"},{"id":"B","text":"B"},{"id":"C","text":"C"},{"id":"D","text":"D"}],"correctAnswer":"c","marks":2,"penalty":0.6666},{"id":"335152","text":"<p>Which of the following cannot be passed to a function in C++?</p>\n\n<ol start=\"1\" style=\"list-style-type:upper-alpha\">\n\t<li>Constant</li>\n\t<li>Structure</li>\n\t<li>Array</li>\n\t<li>Header file</li>\n</ol>","type":"MCQ","options":[{"id":"A","text":"A"},{"id":"B","text":"B"},{"id":"C","text":"C"},{"id":"D","text":"D"}],"correctAnswer":"d","marks":2,"penalty":0.6666}]}]}